bytedzebrastrategy/__init__.py
bytedzebrastrategy-0.0.1.dist-info/METADATA
bytedzebrastrategy-0.0.1.dist-info/WHEEL
bytedzebrastrategy-0.0.1.dist-info/top_level.txt
bytedzebrastrategy-0.0.1.dist-info/RECORD
