Metadata-Version: 2.1
Name: bytedzebrastrategy
Version: 0.0.1
Summary: A simple package named bytedzebrastrategy
Home-page: https://github.com/artifact/bytedzebrastrategy.git
Author: artifact
Author-email: artifact@example.com
License: UNKNOWN
Platform: UNKNOWN
Classifier: Programming Language :: Python :: 3
Classifier: License :: OSI Approved :: MIT License
Classifier: Operating System :: OS Independent
